pytest_tornado5/__init__.py
pytest_tornado5/plugin.py
pytest_tornado5-2.0.0.dist-info/METADATA
pytest_tornado5-2.0.0.dist-info/RECORD
pytest_tornado5-2.0.0.dist-info/WHEEL
pytest_tornado5-2.0.0.dist-info/entry_points.txt
pytest_tornado5-2.0.0.dist-info/top_level.txt
