Metadata-Version: 2.1
Name: pytest-tornado5
Version: 2.0.0
Summary: A py.test plugin providing fixtures and markers to simplify testing of asynchronous tornado applications.
Home-page: https://github.com/vidartf/pytest-tornado
Author: Eugeniy Kalinin
Author-email: burump@gmail.com
Maintainer: Vidar Tonaas Fauske
Maintainer-email: vidartf@gmail.com
License: Apache License, Version 2.0
Keywords: pytest py.test tornado async asynchronous testing unit tests plugin
Platform: UNKNOWN
Classifier: Development Status :: 5 - Production/Stable
Classifier: Environment :: Plugins
Classifier: Intended Audience :: Developers
Classifier: License :: OSI Approved :: Apache Software License
Classifier: Operating System :: OS Independent
Classifier: Programming Language :: Python
Classifier: Programming Language :: Python :: 2
Classifier: Programming Language :: Python :: 3
Classifier: Topic :: Software Development
Classifier: Topic :: Software Development :: Testing
Requires-Dist: pytest (>=3.6)
Requires-Dist: tornado (>=5)
